<?xml version="1.0" encoding="UTF-8"?>
<Configuration status="INFO">
    <Properties>
        <Property name="rawPattern">%d %-5p [%t] %C (%F:%L) - %m%n</Property>
        <Property name="coloredPattern">%d %highlight{%-5p}{FATAL=bright red, ERROR=red, WARN=yellow, INFO=cyan,
            DEBUG=green, TRACE=bright blue} %style{[%t] %C{2} (%F:%L) -}{bright,black} %m%n
        </Property>
        <Property name="coloredShortPattern">%d %highlight{%-5p}{FATAL=bright red, ERROR=red, WARN=yellow, INFO=cyan,
            DEBUG=green, TRACE=bright blue} %style{[%t] -}{bright,black} %m%n
        </Property>
    </Properties>
    <Appenders>
        <Console name="console" target="SYSTEM_OUT">
            <PatternLayout pattern="${rawPattern}"/>
        </Console>
    </Appenders>
    <Loggers>
        <Logger name="org.apache.catalina.startup.DigesterFactory" level="error" />
        <Logger name="org.apache.catalina.util.LifecycleBase" level="error" />
        <Logger name="org.apache.coyote.http11.Http11NioProtocol" level="warn" />
        <logger name="org.apache.sshd.common.util.SecurityUtils" level="warn"/>
        <Logger name="org.apache.tomcat.util.net.NioSelectorPool" level="warn" />
        <Logger name="org.eclipse.jetty.util.component.AbstractLifeCycle" level="error" />
        <Logger name="org.hibernate.validator.internal.util.Version" level="warn" />
        <logger name="org.springframework.boot.actuate.endpoint.jmx" level="warn"/>
        <Root level="debug">
            <AppenderRef ref="console"/>
        </Root>
    </Loggers>
</Configuration>